{
  "posts": [
    {
      "id": "0b5f",
      "title": "",
      "datetime": "February 15, 2024 9:04:18 PM",
      "body": ""
    },
    {
      "id": "0447",
      "title": "",
      "datetime": "February 15, 2024 9:23:43 PM",
      "body": ""
    },
    {
      "id": "57ed",
      "title": "",
      "datetime": "February 15, 2024 9:24:16 PM",
      "body": ""
    },
    {
      "id": "47a2",
      "title": "vervre",
      "datetime": "February 15, 2024 9:30:16 PM",
      "body": "vreverver"
    },
    {
      "id": "4005",
      "title": "fwefwe",
      "datetime": "February 15, 2024 9:30:12 PM",
      "body": "fwefwe"
    },
    {
      "id": "0c78",
      "title": "",
      "datetime": "February 15, 2024 9:54:43 PM",
      "body": ""
    }
  ]
}